fraud_framework_sdk/__init__.py
fraud_framework_sdk/client.py
fraud_framework_sdk/errors.py
fraud_framework_sdk/internal_utils.py
fraud_framework_sdk/py.typed
fraud_framework_sdk/response.py
fraud_framework_sdk-1.0.3.dist-info/LICENSE
fraud_framework_sdk-1.0.3.dist-info/WHEEL
fraud_framework_sdk-1.0.3.dist-info/METADATA
fraud_framework_sdk-1.0.3.dist-info/RECORD
