Metadata-Version: 2.1
Name: fraud-framework-sdk
Version: 1.0.3
Summary: Lightweight Python API to submit risk verification requests and other actions to the Fraud Framework.
Author: mmcclelland1002
Author-email: mmcclelland@thesummitgrp.com
Requires-Python: >=3.8,<4.0
Classifier: Programming Language :: Python :: 3
Classifier: Programming Language :: Python :: 3.10
Classifier: Programming Language :: Python :: 3.8
Classifier: Programming Language :: Python :: 3.9
Requires-Dist: requests (>=2.27.1,<3.0.0)
